soloftpd/__init__.py
soloftpd/app.py
soloftpd/authorizers.py
soloftpd/command.py
soloftpd/config.py
soloftpd/server.py
soloftpd-0.5.1.dist-info/DESCRIPTION.rst
soloftpd-0.5.1.dist-info/METADATA
soloftpd-0.5.1.dist-info/RECORD
soloftpd-0.5.1.dist-info/WHEEL
soloftpd-0.5.1.dist-info/entry_points.txt
soloftpd-0.5.1.dist-info/metadata.json
soloftpd-0.5.1.dist-info/top_level.txt
tests/__init__.py
tests/test_app.py
tests/test_authorizer.py
tests/test_command.py
tests/test_config.py
tests/test_server.py
