Metadata-Version: 2.0
Name: soloftpd
Version: 0.5.1
Summary: FTP server application.
Home-page: https://github.com/tokibito/soloftpd
Author: Shinya Okano
Author-email: tokibito@gmail.com
License: UNKNOWN
Platform: UNKNOWN
Classifier: Development Status :: 3 - Alpha
Classifier: Programming Language :: Python :: 3.4
Classifier: Programming Language :: Python :: 3.5
Classifier: License :: OSI Approved :: MIT License
Requires-Dist: pyftpdlib
